vault_get/__init__.py
vault_get/vault_get.py
vault_get-0.0.1.post1.dist-info/METADATA
vault_get-0.0.1.post1.dist-info/WHEEL
vault_get-0.0.1.post1.dist-info/entry_points.txt
vault_get-0.0.1.post1.dist-info/top_level.txt
vault_get-0.0.1.post1.dist-info/RECORD
