Metadata-Version: 2.1
Name: vault-get
Version: 0.0.1.post1
Summary: Python hvac cli wrapper: get kv from hashicorp vault by auth token or jwt.
Author-email: Alexander Onishchenko <alexonishchenko@gmail.com>
Project-URL: repository, https://github.com/alexonishchenko/vault-get
Project-URL: homepage, https://github.com/alexonishchenko/vault-get
Keywords: vault,kv,secret,hvac
Requires-Python: >=3.11
Requires-Dist: hvac
Provides-Extra: dev
Requires-Dist: black; extra == "dev"
